enum_prop/__init__.py
enum_prop/base.py
enum_prop/py.typed
enum_prop-0.0.1.dist-info/LICENSE
enum_prop-0.0.1.dist-info/METADATA
enum_prop-0.0.1.dist-info/WHEEL
enum_prop-0.0.1.dist-info/top_level.txt
enum_prop-0.0.1.dist-info/RECORD
