Metadata-Version: 2.1
Name: enum-prop
Version: 0.0.1
Summary: Tidy enum properties
Home-page: https://github.com/5monkeys/enum-prop/
Author: Anton Agestam
Author-email: git@antonagestam.se
License: BSD-3-Clause License
Platform: UNKNOWN
Classifier: Intended Audience :: Developers
Classifier: Operating System :: OS Independent
Classifier: Programming Language :: Python
Classifier: Programming Language :: Python :: 3
Classifier: Programming Language :: Python :: 3 :: Only
Classifier: Programming Language :: Python :: 3.9
Classifier: Development Status :: 4 - Beta
Requires-Python: >=3.9
License-File: LICENSE
Provides-Extra: test
Requires-Dist: pytest ; extra == 'test'
Requires-Dist: coverage ; extra == 'test'
